{
  "id": "07-08-rag-admin-management",
  "name": "07-08-rag-admin-management",
  "title": "RAG 管理面板与 Qdrant 同步产品化",
  "description": "把 RAG Orchestrator 从手动同步脚本收口为可在 /assistant/admin 使用的一键状态、初始化与同步能力，补齐 Qdrant collection 初始化和低敏诊断。",
  "status": "in_progress",
  "dev_type": null,
  "scope": null,
  "package": null,
  "priority": "P1",
  "creator": "zhang",
  "assignee": "zhang",
  "createdAt": "2026-07-08",
  "completedAt": null,
  "branch": null,
  "base_branch": "main",
  "worktree_path": null,
  "commit": null,
  "pr_url": null,
  "subtasks": [],
  "children": [],
  "parent": null,
  "relatedFiles": [],
  "notes": "",
  "meta": {}
}