{
  "id": "07-07-round-5-reliability-status-manual-gate-followup",
  "name": "07-07-round-5-reliability-status-manual-gate-followup",
  "title": "Round 5 reliability status manual gate followup",
  "description": "Review reliability status data, synthetic scripts, and carried manual gates; implement one local, public-safe improvement that makes cross-project controllability and platform-gated states easier to verify without live credentials.",
  "status": "completed",
  "dev_type": null,
  "scope": null,
  "package": null,
  "priority": "P1",
  "creator": "zhang",
  "assignee": "zhang",
  "createdAt": "2026-07-07",
  "completedAt": "2026-07-07",
  "branch": null,
  "base_branch": "main",
  "worktree_path": null,
  "commit": null,
  "pr_url": null,
  "subtasks": [],
  "children": [],
  "parent": "07-07-cross-project-autonomous-improvement-round-5",
  "relatedFiles": [],
  "notes": "",
  "meta": {}
}